Metadata-Version: 2.1
Name: texta-embedding
Version: 1.0.3
Summary: texta-embedding
Home-page: https://git.texta.ee/texta/texta-embedding-python
Author: TEXTA
Author-email: info@texta.ee
License: GPLv3
Platform: UNKNOWN
